prometheus_paster.py
prometheus_paster-0.1.1.dist-info/METADATA
prometheus_paster-0.1.1.dist-info/WHEEL
prometheus_paster-0.1.1.dist-info/entry_points.txt
prometheus_paster-0.1.1.dist-info/top_level.txt
prometheus_paster-0.1.1.dist-info/RECORD
