Metadata-Version: 2.1
Name: prometheus-paster
Version: 0.1.1
Summary: prometheus_client and pastedeploy glue
Home-page: https://github.com/hkwi/python-prometheus-paster
Author: Kawai Hiroaki
Author-email: hiroaki.kawai@gmail.com
License: UNKNOWN
Platform: UNKNOWN
Requires-Dist: prometheus-client
